ioe_email_stuff.py
ioe_email_stuff-0.0.13.dist-info/LICENSE
ioe_email_stuff-0.0.13.dist-info/METADATA
ioe_email_stuff-0.0.13.dist-info/WHEEL
ioe_email_stuff-0.0.13.dist-info/top_level.txt
ioe_email_stuff-0.0.13.dist-info/RECORD
