Metadata-Version: 2.1
Name: ioe-email-stuff
Version: 0.0.13
Summary: Email sending functionality package
Home-page: https://github.com/george-oconnor/ioe-email-stuff
Author: george-oconnor (George O' Connor)
Author-email: <george@georgestools.com>
Keywords: python,email,outlook,send email,email attachments,mail
Classifier: Development Status :: 3 - Alpha
Classifier: Intended Audience :: Developers
Classifier: Programming Language :: Python :: 3
Classifier: Operating System :: OS Independent
Classifier: License :: OSI Approved :: MIT License
License-File: LICENSE
